{
  "trade": "plumbers",
  "city": "hamilton",
  "updated": "2026-06-01",
  "regional_cost_note": "Plumbers in Hamilton typically charge $85–$120/hr. Waikato rates are generally 10% lower than Auckland. Emergency callouts add $70–$130.",
  "businesses": [
    {
      "rank": 1,
      "name": "On Tap Plumbing Ltd",
      "rating": 5.0,
      "review_count": 64,
      "suburb": "Whatawhata",
      "phone": "",
      "website": "",
      "known_for": "Professional, punctual plumbing: renovations, new builds, drainage, hot water heating and wood fire installations; Master Plumbers member.",
      "source": "Builderscrack",
      "source_url": "https://builderscrack.co.nz/tradies/1bj35xzw/on-tap-plumbing-ltd",
      "verified": true,
      "verified_date": "2026-06-01"
    },
    {
      "rank": 2,
      "name": "Ur Plumber",
      "rating": 4.3,
      "review_count": 132,
      "suburb": "Hamilton",
      "phone": "",
      "website": "",
      "known_for": "Over 15 years experience in residential, commercial and industrial plumbing, gasfitting, kitchen and bathroom upgrades across the Waikato.",
      "source": "Builderscrack",
      "source_url": "https://builderscrack.co.nz/tradies/2bkse2os/ur-plumber",
      "verified": true,
      "verified_date": "2026-06-01"
    },
    {
      "rank": 3,
      "name": "Farrell Plumbing Ltd",
      "rating": 4.0,
      "review_count": 228,
      "suburb": "Hamilton",
      "phone": "",
      "website": "",
      "known_for": "Hot water cylinder replacement, gas infinity conversions, gas heating and wood burners for Hamilton and wider Waikato.",
      "source": "Builderscrack",
      "source_url": "https://builderscrack.co.nz/tradies/1nmhkx7g/farrell-plumbing-ltd",
      "verified": true,
      "verified_date": "2026-06-01"
    }
  ]
}
